.DS_Store
MaxwellBloch-0.7.1.data/scripts/make-gif-ffmpeg.sh
MaxwellBloch-0.7.1.data/scripts/make-mp4-fixed-frame-2-fields.py
MaxwellBloch-0.7.1.data/scripts/make-mp4-fixed-frame.py
MaxwellBloch-0.7.1.data/scripts/mbsolve
MaxwellBloch-0.7.1.data/scripts/obsolve
maxwellbloch/__init__.py
maxwellbloch/angmom.py
maxwellbloch/field.py
maxwellbloch/fileio.py
maxwellbloch/fixed.py
maxwellbloch/hyperfine.py
maxwellbloch/mb_solve.py
maxwellbloch/ob_atom.py
maxwellbloch/ob_base.py
maxwellbloch/ob_solve.py
maxwellbloch/sigma.py
maxwellbloch/spectral.py
maxwellbloch/t_funcs.py
maxwellbloch/testing.py
maxwellbloch/utility.py
maxwellbloch/version.py
maxwellbloch/tests/__init__.py
maxwellbloch/tests/test_angmom.py
maxwellbloch/tests/test_field.py
maxwellbloch/tests/test_fileio.py
maxwellbloch/tests/test_fixed.py
maxwellbloch/tests/test_hyperfine.py
maxwellbloch/tests/test_mb_solve.py
maxwellbloch/tests/test_ob_atom.py
maxwellbloch/tests/test_ob_solve.py
maxwellbloch/tests/test_sigma.py
maxwellbloch/tests/test_spectral.py
maxwellbloch/tests/test_t_funcs.py
maxwellbloch/tests/test_utility.py
maxwellbloch/tests/json/field-square-0.json
maxwellbloch/tests/json/field-square-1.json
maxwellbloch/tests/json/mb_solve_01.json
maxwellbloch/tests/json/mb_solve_lamda.json
maxwellbloch/tests/json/mb_solve_no_atoms.json
maxwellbloch/tests/json/mb_solve_no_decays.json
maxwellbloch/tests/json/mb_solve_no_rabi_freq_t_func.json
maxwellbloch/tests/json/mbs-two-spectral.json
maxwellbloch/tests/json/mbs_two_gaussian_2pi.json
maxwellbloch/tests/json/mbs_two_gaussian_2pi_n_pi.json
maxwellbloch/tests/json/mbs_two_sech_2pi.json
maxwellbloch/tests/json/mbs_two_sech_2pi_n_pi.json
maxwellbloch/tests/json/ob_atom_02.json
maxwellbloch/tests/json/ob_solve_02.json
maxwellbloch/tests/json/ob_solve_03.json
maxwellbloch/tests/json/obs-two-two-fields.json
maxwellbloch/tests/json/obs-vee-cw-weak-sech-2pi.json
maxwellbloch/tests/json/velocity-classes.json
MaxwellBloch-0.7.1.dist-info/LICENSE.txt
MaxwellBloch-0.7.1.dist-info/METADATA
MaxwellBloch-0.7.1.dist-info/WHEEL
MaxwellBloch-0.7.1.dist-info/top_level.txt
MaxwellBloch-0.7.1.dist-info/RECORD
