Metadata-Version: 2.1
Name: MaxwellBloch
Version: 0.7.1
Summary: A Python package for solving the Maxwell-Bloch equations.
Home-page: http://github.com/tpogden/maxwellbloch
Author: Thomas P Ogden
Author-email: t@ogden.eu
License: MIT
Platform: UNKNOWN
Requires-Dist: qutip
